photontracer/__init__.py
photontracer-0.0.0.dist-info/METADATA
photontracer-0.0.0.dist-info/WHEEL
photontracer-0.0.0.dist-info/top_level.txt
photontracer-0.0.0.dist-info/RECORD
