Metadata-Version: 2.4
Name: photontracer
Version: 0.0.0
Summary: GPU acceleraced light scattering simulation
Author-email: Rafael Ottersberg <rafael.ottersberg@unibe.ch>
